aes256.py
sfer.py
sfer-0.0.3.dist-info/METADATA
sfer-0.0.3.dist-info/WHEEL
sfer-0.0.3.dist-info/entry_points.txt
sfer-0.0.3.dist-info/top_level.txt
sfer-0.0.3.dist-info/RECORD
